{
    "version": 1,
    "license": "CC-BY-SA-3.0",
    "copyright": "Created by discord: Mascot_valeraCreated for Adventure Time. bowl Taken from tgstation and modified by Swept at https://github.com/tgstation/tgstation/commit/40d75cc340c63582fb66ce15bf75a36115f6bdaa. escargot from tgstation at https://github.com/tgstation/tgstation/commit/7ffd61b6fa6a6183daa8900f9a490f46f7a81955.",
    "size": {
        "x": 32,
        "y": 32
    },
    "states": [

        {
            "name": "bowl"
        },
        {
            "name": "soupsawdust"
        }
    ]
}
