{
  "version": 1,
  "license": "CC-BY-SA-3.0",
  "copyright": "Taken from shiptest at commit https://github.com/shiptest-ss13/Shiptest/pull/1933/commits/c83640f260c822b4e5f6dfad19906df233f80fa7 & icon made by github:Morb0. Vox state made by Flareguy for SS14, equipped-OUTERCLOTHING-resomi made by svarshiksatanist (Discord)",
  "size": {
    "x": 32,
    "y": 32
  },
  "states": [
    {
      "name": "icon"
    },
    {
      "name": "equipped-OUTERCLOTHING",
      "directions": 4
    },
    {
      "name": "equipped-OUTERCLOTHING-vox",
      "directions": 4
    },
    {
      "name": "equipped-OUTERCLOTHING-resomi",
      "directions": 4
    },
    {
      "name": "inhand-left",
      "directions": 4
    },
    {
      "name": "inhand-right",
      "directions": 4
    }
  ]
}
